fs/onedrivefs/__init__.py
fs/onedrivefs/onedrivefs.py
fs/onedrivefs/opener.py
fs/onedrivefs/throttling.py
fs_onedrivefs-1.2.3.dist-info/METADATA
fs_onedrivefs-1.2.3.dist-info/WHEEL
fs_onedrivefs-1.2.3.dist-info/entry_points.txt
fs_onedrivefs-1.2.3.dist-info/licenses/LICENSE
fs_onedrivefs-1.2.3.dist-info/RECORD
