Metadata-Version: 2.4
Name: fs.onedrivefs
Version: 1.2.3
Summary: Pyfilesystem2 implementation for OneDrive using Microsoft Graph API
Project-URL: Homepage, https://github.com/rkhwaja/fs.onedrivefs
Maintainer-email: Rehan KHwaja <rehan@khwaja.name>
License-Expression: MIT
License-File: LICENSE
Keywords: Pyfilesystem2,filesystem,onedrive
Classifier: Development Status :: 5 - Production/Stable
Classifier: Intended Audience :: Developers
Classifier: Programming Language :: Python :: 3.8
Classifier: Programming Language :: Python :: 3.9
Classifier: Programming Language :: Python :: 3.10
Classifier: Programming Language :: Python :: 3.11
Classifier: Programming Language :: Python :: 3.12
Classifier: Programming Language :: Python :: 3.13
Classifier: Programming Language :: Python :: 3.14
Requires-Python: >=3.8
Requires-Dist: fs<3,>=2.4.13
Requires-Dist: requests-oauthlib>=1.2.0
Requires-Dist: requests>=2.20
